LICENSE
README.md
setup.cfg
setup.py
tendermintwallet/__init__.py
tendermintwallet/_transaction.py
tendermintwallet/_typing.py
tendermintwallet/_wallet.py
tendermintwallet.egg-info/PKG-INFO
tendermintwallet.egg-info/SOURCES.txt
tendermintwallet.egg-info/dependency_links.txt
tendermintwallet.egg-info/not-zip-safe
tendermintwallet.egg-info/requires.txt
tendermintwallet.egg-info/top_level.txt
tendermintwallet/interfaces/__init__.py
tendermintwallet/interfaces/any_pb2.py
tendermintwallet/interfaces/coin_pb2.py
tendermintwallet/interfaces/gogo_pb2.py
tendermintwallet/interfaces/msg_send_pb2.py
tendermintwallet/interfaces/pubkey_pb2.py
tendermintwallet/interfaces/signing_pb2.py
tendermintwallet/interfaces/tx_pb2.py