Metadata-Version: 2.1
Name: tendermintwallet
Version: 0.0.2
Summary: Tools for tendermint-based wallet management, offline transaction signing and broadcasting
Home-page: https://github.com/algo-vaultstaking/tendermintwallet
Author: AlgoRhythm
Author-email: 
License: MIT
Platform: UNKNOWN
License-File: LICENSE
